ecpay_invoice/__init__.py
ecpay_invoice/ecpay_main.py
ecpay_invoice/ecpay_setting.py
ecpay_invoice3-1.1.2.dist-info/LICENSE
ecpay_invoice3-1.1.2.dist-info/LICENSE.txt
ecpay_invoice3-1.1.2.dist-info/METADATA
ecpay_invoice3-1.1.2.dist-info/WHEEL
ecpay_invoice3-1.1.2.dist-info/top_level.txt
ecpay_invoice3-1.1.2.dist-info/RECORD
