Metadata-Version: 2.1
Name: ecpay-invoice3
Version: 1.1.2
Summary: ecpay_invoice3
Home-page: https://github.com/skypc785308/ecpay_invoice3
Author: Hiskyz
Author-email: skypc785308@gmail.com
License: Apache 2.0 License
Platform: UNKNOWN
Classifier: Development Status :: 5 - Production/Stable
Classifier: Operating System :: OS Independent
Classifier: Intended Audience :: Financial and Insurance Industry
Classifier: License :: OSI Approved :: BSD License
Classifier: Programming Language :: Python
Classifier: Programming Language :: Python :: 3.6
Classifier: Topic :: Software Development :: Libraries
Requires-Dist: requests
